README.rst
setup.py
cql_kernel/__init__.py
cql_kernel/__main__.py
cql_kernel/cql_html_format.py
cql_kernel/cqlsh.py
cql_kernel/images.py
cql_kernel/install.py
cql_kernel/kernel.py
cql_kernel.egg-info/PKG-INFO
cql_kernel.egg-info/SOURCES.txt
cql_kernel.egg-info/dependency_links.txt
cql_kernel.egg-info/top_level.txt
cql_kernel/lib/cassandra-driver-internal-only-3.0.0-6af642d.zip
cql_kernel/lib/futures-2.1.6-py2.py3-none-any.zip
cql_kernel/lib/six-1.7.3-py2.py3-none-any.zip
cqlshlib_cql_kernel/__init__.py
cqlshlib_cql_kernel/copyutil.py
cqlshlib_cql_kernel/cql3handling.py
cqlshlib_cql_kernel/cqlhandling.py
cqlshlib_cql_kernel/displaying.py
cqlshlib_cql_kernel/formatting.py
cqlshlib_cql_kernel/helptopics.py
cqlshlib_cql_kernel/pylexotron.py
cqlshlib_cql_kernel/saferscanner.py
cqlshlib_cql_kernel/sslhandling.py
cqlshlib_cql_kernel/tracing.py
cqlshlib_cql_kernel/util.py
cqlshlib_cql_kernel/wcwidth.py
cqlshlib_cql_kernel/test/__init__.py
cqlshlib_cql_kernel/test/ansi_colors.py
cqlshlib_cql_kernel/test/basecase.py
cqlshlib_cql_kernel/test/cassconnect.py
cqlshlib_cql_kernel/test/run_cqlsh.py
cqlshlib_cql_kernel/test/test_cql_parsing.py
cqlshlib_cql_kernel/test/test_cqlsh_commands.py
cqlshlib_cql_kernel/test/test_cqlsh_completion.py
cqlshlib_cql_kernel/test/test_cqlsh_invocation.py
cqlshlib_cql_kernel/test/test_cqlsh_output.py
cqlshlib_cql_kernel/test/test_cqlsh_parsing.py
cqlshlib_cql_kernel/test/winpty.py