Metadata-Version: 1.0
Name: cql-kernel
Version: 3.0.1
Summary: CQL Kernel for Jupyter based on cqlsh
Home-page: https://github.com/slowenthal/cql_kernel
Author: Steven Lowenthal & Apache Cassandra Developers
Author-email: steve@datastax.com
License: Apache
Platform: UNKNOWN
